cloud/__init__.py
cloud/cloud.py
cloud/envs/__init__.py
cloud/envs/aws.py
cloud/envs/azure.py
cloud/envs/env.py
cloud/envs/gcp.py
cloud/envs/registry.py
cloud/envs/utils.py
dl_cloud-0.2.2.dist-info/LICENSE
dl_cloud-0.2.2.dist-info/METADATA
dl_cloud-0.2.2.dist-info/WHEEL
dl_cloud-0.2.2.dist-info/top_level.txt
dl_cloud-0.2.2.dist-info/RECORD
