Metadata-Version: 2.1
Name: dl-cloud
Version: 0.2.2
Summary: Cloud resource management for deep learning applications.
Home-page: https://github.com/for-ai/cloud
Author: FOR.ai
Author-email: team@for.ai
License: UNKNOWN
Keywords: deep learning cloud
Platform: UNKNOWN
Classifier: Development Status :: 3 - Alpha
Classifier: Intended Audience :: Developers
Classifier: License :: OSI Approved :: MIT License
Classifier: Programming Language :: Python :: 3.5
License-File: LICENSE
Requires-Dist: numpy
Requires-Dist: apache-libcloud
Requires-Dist: toml
Requires-Dist: errand-boy
Requires-Dist: filelock
